Metadata-Version: 2.1
Name: odoo9-addon-l10n-ch-fds-postfinance
Version: 9.0.1.0.0.99.dev30
Summary: Download files and import bank statements from FDS
Home-page: http://www.compassion.ch/
Author: Compassion CH, Odoo Community Association (OCA)
Author-email: support@odoo-community.org
License: AGPL-3
Platform: UNKNOWN
Classifier: Programming Language :: Python
Classifier: Framework :: Odoo
Classifier: Framework :: Odoo :: 9.0
Classifier: License :: OSI Approved :: GNU Affero General Public License v3
Requires-Python: ~=2.7
Requires-Dist: Crypto
Requires-Dist: odoo (<9.1a,>=9.0a)
Requires-Dist: pysftp
